flask_email_verifier.py
Flask_EmailVerifier-0.1.0.dist-info/LICENSE
Flask_EmailVerifier-0.1.0.dist-info/METADATA
Flask_EmailVerifier-0.1.0.dist-info/WHEEL
Flask_EmailVerifier-0.1.0.dist-info/top_level.txt
Flask_EmailVerifier-0.1.0.dist-info/RECORD
