Metadata-Version: 1.1
Name: Flask-EmailVerifier
Version: 0.1.0
Summary: The simplest library for email verification for Flask.
Home-page: https://github.com/whois-api-llc/flask-email-verifier
Author: Whois API, Inc.
Author-email: support@whoisxmlapi.com
License: MIT
Platform: any
Classifier: Environment :: Web Environment
Classifier: Intended Audience :: Developers
Classifier: License :: OSI Approved :: MIT License
Classifier: Operating System :: OS Independent
Classifier: Programming Language :: Python
Classifier: Topic :: Internet :: WWW/HTTP :: Dynamic Content
Classifier: Topic :: Software Development :: Libraries :: Python Modules
